cupy/__init__.py
cupy/_environment.py
cupy/_version.py
cupy/cudnn.cpython-37m-x86_64-linux-gnu.so
cupy/cusparse.py
cupy/cutensor.py
cupy/util.cpython-37m-x86_64-linux-gnu.so
cupy/.data/include/cudnn.h
cupy/.data/lib/libcudnn.so.7
cupy/.data/lib/libnccl.so.2
cupy/binary/__init__.py
cupy/binary/elementwise.py
cupy/binary/packing.py
cupy/core/__init__.py
cupy/core/_dtype.cpython-37m-x86_64-linux-gnu.so
cupy/core/_errors.py
cupy/core/_kernel.cpython-37m-x86_64-linux-gnu.so
cupy/core/_memory_range.cpython-37m-x86_64-linux-gnu.so
cupy/core/_routines_indexing.cpython-37m-x86_64-linux-gnu.so
cupy/core/_routines_logic.cpython-37m-x86_64-linux-gnu.so
cupy/core/_routines_manipulation.cpython-37m-x86_64-linux-gnu.so
cupy/core/_routines_math.cpython-37m-x86_64-linux-gnu.so
cupy/core/_routines_sorting.cpython-37m-x86_64-linux-gnu.so
cupy/core/_routines_statistics.cpython-37m-x86_64-linux-gnu.so
cupy/core/_scalar.cpython-37m-x86_64-linux-gnu.so
cupy/core/_ufuncs.py
cupy/core/core.cpython-37m-x86_64-linux-gnu.so
cupy/core/dlpack.cpython-37m-x86_64-linux-gnu.so
cupy/core/flags.cpython-37m-x86_64-linux-gnu.so
cupy/core/fusion.cpython-37m-x86_64-linux-gnu.so
cupy/core/internal.cpython-37m-x86_64-linux-gnu.so
cupy/core/raw.cpython-37m-x86_64-linux-gnu.so
cupy/core/include/cupy/atomics.cuh
cupy/core/include/cupy/carray.cuh
cupy/core/include/cupy/complex.cuh
cupy/core/include/cupy/cuComplex_bridge.h
cupy/core/include/cupy/_cuda/cuda-10.0/cuda_fp16.h
cupy/core/include/cupy/_cuda/cuda-10.0/cuda_fp16.hpp
cupy/core/include/cupy/_cuda/cuda-10.1/cuda_fp16.h
cupy/core/include/cupy/_cuda/cuda-10.1/cuda_fp16.hpp
cupy/core/include/cupy/_cuda/cuda-10.2/cuda_fp16.h
cupy/core/include/cupy/_cuda/cuda-10.2/cuda_fp16.hpp
cupy/core/include/cupy/_cuda/cuda-11.0/cuda_fp16.h
cupy/core/include/cupy/_cuda/cuda-11.0/cuda_fp16.hpp
cupy/core/include/cupy/_cuda/cuda-9.2/cuda_fp16.h
cupy/core/include/cupy/_cuda/cuda-9.2/cuda_fp16.hpp
cupy/core/include/cupy/complex/arithmetic.h
cupy_cuda80-7.8.0.dist-info/METADATA
cupy_cuda80-7.8.0.dist-info/WHEEL
cupy_cuda80-7.8.0.dist-info/license.rst
cupy_cuda80-7.8.0.dist-info/top_level.txt
cupy_cuda80-7.8.0.dist-info/RECORD
